Metadata-Version: 2.1
Name: req1
Version: 0.2
Summary: your description
Home-page: UNKNOWN
Author: AFRITON
License: UNKNOWN
Platform: UNKNOWN
Classifier: Programming Language :: Python :: 3
Classifier: Operating System :: OS Independent
Classifier: License :: OSI Approved :: MIT License
License-File: LICENSE.txt
